netLocator/__init__.py
netLocator/netLocator.py
netLocator-1.0.0.dist-info/LICENSE.txt
netLocator-1.0.0.dist-info/METADATA
netLocator-1.0.0.dist-info/WHEEL
netLocator-1.0.0.dist-info/top_level.txt
netLocator-1.0.0.dist-info/RECORD
