Metadata-Version: 2.1
Name: netLocator
Version: 1.0.0
Summary: Quickly retrieve the current IPv4 address of your machine.
Author: Yasiru Perera
Author-email: yasiruperera681@gmail.com
Keywords: python,network,IP address,IPv4,network utilities
Classifier: Development Status :: 5 - Production/Stable
Classifier: Intended Audience :: Developers
Classifier: Programming Language :: Python :: 3
Classifier: License :: OSI Approved :: MIT License
Classifier: Operating System :: Microsoft :: Windows
License-File: LICENSE.txt
Requires-Dist: subprocess
